HimanshuJain2024AAPS0780G/rtl/minutes_counter.v
module minutes_counter (
    input  wire clk,
    input  wire rst_n,
    input  wire enable,
    input  wire rollover,   // from seconds

    output reg [7:0] minutes
);

    always @(posedge clk or negedge rst_n) begin

        if (!rst_n) begin
            minutes <= 8'd0;
        end
        else begin

            if (enable && rollover) begin

                if (minutes == 8'd99)
                    minutes <= 8'd0;
                else
                    minutes <= minutes + 1'b1;

            end

        end

    end

endmodule

HimanshuJain2024AAPS0780G/rtl/seconds_counter.v
module seconds_counter (
    input  wire clk,
    input  wire rst_n,
    input  wire enable,

    output reg  [5:0] seconds,
    output reg  rollover
);

    always @(posedge clk or negedge rst_n) begin
        if (!rst_n) begin
            seconds  <= 6'd0;
            rollover <= 1'b0;
        end
        else begin
            rollover <= 1'b0;

            if (enable) begin

                if (seconds == 6'd59) begin
                    seconds  <= 6'd0;
                    rollover <= 1'b1;
                end
                else begin
                    seconds <= seconds + 1'b1;
                end

            end
        end
    end

endmodule

HimanshuJain2024AAPS0780G/rtl/control_fsm.v
module control_fsm (
    input  wire clk,
    input  wire rst_n,
    input  wire start,
    input  wire stop,
    input  wire reset,

    output reg  enable,
    output reg  [1:0] status
);

    // State encoding
    localparam IDLE    = 2'b00;
    localparam RUNNING = 2'b01;
    localparam PAUSED  = 2'b10;

    reg [1:0] state, next_state;

    // ----------------------------
    // State Register
    // ----------------------------

    always @(posedge clk or negedge rst_n) begin
        if (!rst_n)
            state <= IDLE;
        else
            state <= next_state;
    end

    // ----------------------------
    // Next State Logic
    // ----------------------------

    always @(*) begin

        next_state = state;

        case (state)

            IDLE: begin
                if (start)
                    next_state = RUNNING;
            end

            RUNNING: begin
                if (stop)
                    next_state = PAUSED;
                else if (reset)
                    next_state = IDLE;
            end

            PAUSED: begin
                if (start)
                    next_state = RUNNING;
                else if (reset)
                    next_state = IDLE;
            end

            default: next_state = IDLE;

        endcase
    end

    // ----------------------------
    // Output Logic
    // ----------------------------

    always @(*) begin

        status = state;

        case (state)

            RUNNING: enable = 1'b1;
            default: enable = 1'b0;

        endcase
    end

endmodule

HimanshuJain2024AAPS0780G/rtl/stopwatch_top.v
module stopwatch_top (
    input  wire clk,
    input  wire rst_n,
    input  wire start,
    input  wire stop,
    input  wire reset,

    output wire [7:0] minutes,
    output wire [5:0] seconds,
    output wire [1:0] status
);

    // Internal wires
    wire enable;
    wire sec_rollover;

    // Control FSM
    control_fsm fsm (
        .clk    (clk),
        .rst_n  (rst_n),
        .start  (start),
        .stop   (stop),
        .reset  (reset),
        .enable (enable),
        .status (status)
    );

    // Seconds Counter
    seconds_counter sec (
        .clk      (clk),
        .rst_n    (rst_n),
        .enable   (enable),
        .seconds  (seconds),
        .rollover (sec_rollover)   // <<< IMPORTANT
    );

    // Minutes Counter
    minutes_counter min (
        .clk      (clk),
        .rst_n    (rst_n),
        .enable   (enable),
        .rollover (sec_rollover),  // <<< IMPORTANT
        .minutes  (minutes)
    );

endmodule

HimanshuJain2024AAPS0780G/tb/tb_stopwatch.v
`timescale 1ns/1ps

module tb_stopwatch;

    // Inputs
    reg clk;
    reg rst_n;
    reg start;
    reg stop;
    reg reset;

    // Outputs
    wire [7:0] minutes;
    wire [5:0] seconds;
    wire [1:0] status;

    // Instantiate DUT (Device Under Test)
    stopwatch_top dut (
        .clk     (clk),
        .rst_n   (rst_n),
        .start   (start),
        .stop    (stop),
        .reset   (reset),
        .minutes (minutes),
        .seconds (seconds),
        .status  (status)
    );

    // ============================
    // Clock Generator (10ns period)
    // ============================

    always #5 clk = ~clk;

    // ============================
    // Test Sequence
    // ============================

    initial begin

        // Dump for GTKWave
        $dumpfile("wave.vcd");
        $dumpvars(0, tb_stopwatch);

        // Initial values
        clk   = 0;
        rst_n = 0;
        start = 0;
        stop  = 0;
        reset = 0;

        // Hold reset
        #20;
        rst_n = 1;

        // ============================
        // Start Stopwatch
        // ============================

        #10;
        start = 1;
        #10;
        start = 0;

        // Let it run (10 seconds)
        #200;

        // ============================
        // Pause
        // ============================

        stop = 1;
        #10;
        stop = 0;

        // Stay paused
        #100;

        // ============================
        // Resume
        // ============================

        start = 1;
        #10;
        start = 0;

        // Run again
        #200;

        // ============================
        // Reset
        // ============================

        reset = 1;
        #10;
        reset = 0;
        // Start again after reset
        #20;
        start = 1;
        #10;
        start = 0;

        // Wait
        #500000;

        // Finish simulation
        $finish;

    end

    // ============================
    // Monitor Output (Console)
    // ============================

    always @(posedge clk) begin

        $display("Time = %0t | %02d:%02d | State = %b",
                 $time,
                 minutes,
                 seconds,
                 status);

    end

endmodule

HimanshuJain2024AAPS0780G/tb/wave.vcd
$date
	Mon Feb  2 22:41:53 2026
$end
$version
	Icarus Verilog
$end
$timescale
	1ps
$end
$scope module tb_stopwatch $end
$var wire 2 ! status [1:0] $end
$var wire 6 " seconds [5:0] $end
$var wire 8 # minutes [7:0] $end
$var reg 1 $ clk $end
$var reg 1 % reset $end
$var reg 1 & rst_n $end
$var reg 1 ' start $end
$var reg 1 ( stop $end
$scope module dut $end
$var wire 1 $ clk $end
$var wire 1 % reset $end
$var wire 1 & rst_n $end
$var wire 1 ' start $end
$var wire 1 ( stop $end
$var wire 2 ) status [1:0] $end
$var wire 6 * seconds [5:0] $end
$var wire 1 + sec_rollover $end
$var wire 8 , minutes [7:0] $end
$var wire 1 - enable $end
$scope module fsm $end
$var wire 1 $ clk $end
$var wire 1 % reset $end
$var wire 1 & rst_n $end
$var wire 1 ' start $end
$var wire 1 ( stop $end
$var parameter 2 . IDLE $end
$var parameter 2 / PAUSED $end
$var parameter 2 0 RUNNING $end
$var reg 1 - enable $end
$var reg 2 1 next_state [1:0] $end
$var reg 2 2 state [1:0] $end
$var reg 2 3 status [1:0] $end
$upscope $end
$scope module min $end
$var wire 1 $ clk $end
$var wire 1 - enable $end
$var wire 1 & rst_n $end
$var wire 1 + rollover $end
$var reg 8 4 minutes [7:0] $end
$upscope $end
$scope module sec $end
$var wire 1 $ clk $end
$var wire 1 - enable $end
$var wire 1 & rst_n $end
$var reg 1 + rollover $end
$var reg 6 5 seconds [5:0] $end
$upscope $end
$upscope $end
$upscope $end
$enddefinitions $end
$comment Show the parameter values. $end
$dumpall
b1 0
b10 /
b0 .
$end
#0
$dumpvars
b0 5
b0 4
b0 3
b0 2
b0 1
0-
b0 ,
0+
b0 *
b0 )
0(
0'
0&
0%
0$
b0 #
b0 "
b0 !
$end
#5000
1$
#10000
0$
#15000
1$
#20000
0$
1&
#25000
1$
#30000
b1 1
0$
1'
#35000
1-
b1 !
b1 )
b1 3
b1 2
1$
#40000
0$
0'
#45000
b1 "
b1 *
b1 5
1$
#50000
0$
#55000
b10 "
b10 *
b10 5
1$
#60000
0$
#65000
b11 "
b11 *
b11 5
1$
#70000
0$
#75000
b100 "
b100 *
b100 5
1$
#80000
0$
#85000
b101 "
b101 *
b101 5
1$
#90000
0$
#95000
b110 "
b110 *
b110 5
1$
#100000
0$
#105000
b111 "
b111 *
b111 5
1$
#110000
0$
#115000
b1000 "
b1000 *
b1000 5
1$
#120000
0$
#125000
b1001 "
b1001 *
b1001 5
1$
#130000
0$
#135000
b1010 "
b1010 *
b1010 5
1$
#140000
0$
#145000
b1011 "
b1011 *
b1011 5
1$
#150000
0$
#155000
b1100 "
b1100 *
b1100 5
1$
#160000
0$
#165000
b1101 "
b1101 *
b1101 5
1$
#170000
0$
#175000
b1110 "
b1110 *
b1110 5
1$
#180000
0$
#185000
b1111 "
b1111 *
b1111 5
1$
#190000
0$
#195000
b10000 "
b10000 *
b10000 5
1$
#200000
0$
#205000
b10001 "
b10001 *
b10001 5
1$
#210000
0$
#215000
b10010 "
b10010 *
b10010 5
1$
#220000
0$
#225000
b10011 "
b10011 *
b10011 5
1$
#230000
0$
#235000
b10100 "
b10100 *
b10100 5
1$
#240000
b10 1
0$
1(
#245000
0-
b10 !
b10 )
b10 3
b10101 "
b10101 *
b10101 5
b10 2
1$
#250000
0$
0(
#255000
1$
#260000
0$
#265000
1$
#270000
0$
#275000
1$
#280000
0$
#285000
1$
#290000
0$
#295000
1$
#300000
0$
#305000
1$
#310000
0$
#315000
1$
#320000
0$
#325000
1$
#330000
0$
#335000
1$
#340000
0$
#345000
1$
#350000
b1 1
0$
1'
#355000
1-
b1 !
b1 )
b1 3
b1 2
1$
#360000
0$
0'
#365000
b10110 "
b10110 *
b10110 5
1$
#370000
0$
#375000
b10111 "
b10111 *
b10111 5
1$
#380000
0$
#385000
b11000 "
b11000 *
b11000 5
1$
#390000
0$
#395000
b11001 "
b11001 *
b11001 5
1$
#400000
0$
#405000
b11010 "
b11010 *
b11010 5
1$
#410000
0$
#415000
b11011 "
b11011 *
b11011 5
1$
#420000
0$
#425000
b11100 "
b11100 *
b11100 5
1$
#430000
0$
#435000
b11101 "
b11101 *
b11101 5
1$
#440000
0$
#445000
b11110 "
b11110 *
b11110 5
1$
#450000
0$
#455000
b11111 "
b11111 *
b11111 5
1$
#460000
0$
#465000
b100000 "
b100000 *
b100000 5
1$
#470000
0$
#475000
b100001 "
b100001 *
b100001 5
1$
#480000
0$
#485000
b100010 "
b100010 *
b100010 5
1$
#490000
0$
#495000
b100011 "
b100011 *
b100011 5
1$
#500000
0$
#505000
b100100 "
b100100 *
b100100 5
1$
#510000
0$
#515000
b100101 "
b100101 *
b100101 5
1$
#520000
0$
#525000
b100110 "
b100110 *
b100110 5
1$
#530000
0$
#535000
b100111 "
b100111 *
b100111 5
1$
#540000
0$
#545000
b101000 "
b101000 *
b101000 5
1$
#550000
0$
#555000
b101001 "
b101001 *
b101001 5
1$
#560000
b0 1
0$
1%
#565000
0-
b0 !
b0 )
b0 3
b101010 "
b101010 *
b101010 5
b0 2
1$
#570000
0$
0%
#575000
1$
#580000
0$
#585000
1$
#590000
b1 1
0$
1'
#595000
1-
b1 !
b1 )
b1 3
b1 2
1$
#600000
0$
0'
#605000
b101011 "
b101011 *
b101011 5
1$
#610000
0$
#615000
b101100 "
b101100 *
b101100 5
1$
#620000
0$
#625000
b101101 "
b101101 *
b101101 5
1$
#630000
0$
#635000
b101110 "
b101110 *
b101110 5
1$
#640000
0$
#645000
b101111 "
b101111 *
b101111 5
1$
#650000
0$
#655000
b110000 "
b110000 *
b110000 5
1$
#660000
0$
#665000
b110001 "
b110001 *
b110001 5
1$
#670000
0$
#675000
b110010 "
b110010 *
b110010 5
1$
#680000
0$
#685000
b110011 "
b110011 *
b110011 5
1$
#690000
0$
#695000
b110100 "
b110100 *
b110100 5
1$
#700000
0$
#705000
b110101 "
b110101 *
b110101 5
1$
#710000
0$
#715000
b110110 "
b110110 *
b110110 5
1$
#720000
0$
#725000
b110111 "
b110111 *
b110111 5
1$
#730000
0$
#735000
b111000 "
b111000 *
b111000 5
1$
#740000
0$
#745000
b111001 "
b111001 *
b111001 5
1$
#750000
0$
#755000
b111010 "
b111010 *
b111010 5
1$
#760000
0$
#765000
b111011 "
b111011 *
b111011 5
1$
#770000
0$
#775000
1+
b0 "
b0 *
b0 5
1$
#780000
0$
#785000
b1 #
b1 ,
b1 4
b1 "
b1 *
b1 5
0+
1$
#790000
0$
#795000
b10 "
b10 *
b10 5
1$
#800000
0$
#805000
b11 "
b11 *
b11 5
1$
#810000
0$
#815000
b100 "
b100 *
b100 5
1$
#820000
0$
#825000
b101 "
b101 *
b101 5
1$
#830000
0$
#835000
b110 "
b110 *
b110 5
1$
#840000
0$
#845000
b111 "
b111 *
b111 5
1$
#850000
0$
#855000
b1000 "
b1000 *
b1000 5
1$
#860000
0$
#865000
b1001 "
b1001 *
b1001 5
1$
#870000
0$
#875000
b1010 "
b1010 *
b1010 5
1$
#880000
0$
#885000
b1011 "
b1011 *
b1011 5
1$
#890000
0$
#895000
b1100 "
b1100 *
b1100 5
1$
#900000
0$
#905000
b1101 "
b1101 *
b1101 5
1$
#910000
0$
#915000
b1110 "
b1110 *
b1110 5
1$
#920000
0$
#925000
b1111 "
b1111 *
b1111 5
1$
#930000
0$
#935000
b10000 "
b10000 *
b10000 5
1$
#940000
0$
#945000
b10001 "
b10001 *
b10001 5
1$
#950000
0$
#955000
b10010 "
b10010 *
b10010 5
1$
#960000
0$
#965000
b10011 "
b10011 *
b10011 5
1$
#970000
0$
#975000
b10100 "
b10100 *
b10100 5
1$
#980000
0$
#985000
b10101 "
b10101 *
b10101 5
1$
#990000
0$
#995000
b10110 "
b10110 *
b10110 5
1$
#1000000
0$
#1005000
b10111 "
b10111 *
b10111 5
1$
#1010000
0$
#1015000
b11000 "
b11000 *
b11000 5
1$
#1020000
0$
#1025000
b11001 "
b11001 *
b11001 5
1$
#1030000
0$
#1035000
b11010 "
b11010 *
b11010 5
1$
#1040000
0$
#1045000
b11011 "
b11011 *
b11011 5
1$
#1050000
0$
#1055000
b11100 "
b11100 *
b11100 5
1$
#1060000
0$
#1065000
b11101 "
b11101 *
b11101 5
1$
#1070000
0$
#1075000
b11110 "
b11110 *
b11110 5
1$
#1080000
0$
#1085000
b11111 "
b11111 *
b11111 5
1$
#1090000
0$
#1095000
b100000 "
b100000 *
b100000 5
1$
#1100000
0$
#1105000
b100001 "
b100001 *
b100001 5
1$
#1110000
0$
#1115000
b100010 "
b100010 *
b100010 5
1$
#1120000
0$
#1125000
b100011 "
b100011 *
b100011 5
1$
#1130000
0$
#1135000
b100100 "
b100100 *
b100100 5
1$
#1140000
0$
#1145000
b100101 "
b100101 *
b100101 5
1$
#1150000
0$
#1155000
b100110 "
b100110 *
b100110 5
1$
#1160000
0$
#1165000
b100111 "
b100111 *
b100111 5
1$
#1170000
0$
#1175000
b101000 "
b101000 *
b101000 5
1$
#1180000
0$
#1185000
b101001 "
b101001 *
b101001 5
1$
#1190000
0$
#1195000
b101010 "
b101010 *
b101010 5
1$
#1200000
0$
#1205000
b101011 "
b101011 *
b101011 5
1$
#1210000
0$
#1215000
b101100 "
b101100 *
b101100 5
1$
#1220000
0$
#1225000
b101101 "
b101101 *
b101101 5
1$
#1230000
0$
#1235000
b101110 "
b101110 *
b101110 5
1$
#1240000
0$
#1245000
b101111 "
b101111 *
b101111 5
1$
#1250000
0$
#1255000
b110000 "
b110000 *
b110000 5
1$
#1260000
0$
#1265000
b110001 "
b110001 *
b110001 5
1$
#1270000
0$
#1275000
b110010 "
b110010 *
b110010 5
1$
#1280000
0$
#1285000
b110011 "
b110011 *
b110011 5
1$
#1290000
0$
#1295000
b110100 "
b110100 *
b110100 5
1$
#1300000
0$
#1305000
b110101 "
b110101 *
b110101 5
1$
#1310000
0$
#1315000
b110110 "
b110110 *
b110110 5
1$
#1320000
0$
#1325000
b110111 "
b110111 *
b110111 5
1$
#1330000
0$
#1335000
b111000 "
b111000 *
b111000 5
1$
#1340000
0$
#1345000
b111001 "
b111001 *
b111001 5
1$
#1350000
0$
#1355000
b111010 "
b111010 *
b111010 5
1$
#1360000
0$
#1365000
b111011 "
b111011 *
b111011 5
1$
#1370000
0$
#1375000
1+
b0 "
b0 *
b0 5
1$
#1380000
0$
#1385000
b10 #
b10 ,
b10 4
b1 "
b1 *
b1 5
0+
1$
#1390000
0$
#1395000
b10 "
b10 *
b10 5
1$
#1400000
0$
#1405000
b11 "
b11 *
b11 5
1$
#1410000
0$
#1415000
b100 "
b100 *
b100 5
1$
#1420000
0$
#1425000
b101 "
b101 *
b101 5
1$
#1430000
0$
#1435000
b110 "
b110 *
b110 5
1$
#1440000
0$
#1445000
b111 "
b111 *
b111 5
1$
#1450000
0$
#1455000
b1000 "
b1000 *
b1000 5
1$
#1460000
0$
#1465000
b1001 "
b1001 *
b1001 5
1$
#1470000
0$
#1475000
b1010 "
b1010 *
b1010 5
1$
#1480000
0$
#1485000
b1011 "
b1011 *
b1011 5
1$
#1490000
0$
#1495000
b1100 "
b1100 *
b1100 5
1$
#1500000
0$
#1505000
b1101 "
b1101 *
b1101 5
1$
#1510000
0$
#1515000
b1110 "
b1110 *
b1110 5
1$
#1520000
0$
#1525000
b1111 "
b1111 *
b1111 5
1$
#1530000
0$
#1535000
b10000 "
b10000 *
b10000 5
1$
#1540000
0$
#1545000
b10001 "
b10001 *
b10001 5
1$
#1550000
0$
#1555000
b10010 "
b10010 *
b10010 5
1$
#1560000
0$
#1565000
b10011 "
b10011 *
b10011 5
1$
#1570000
0$
#1575000
b10100 "
b10100 *
b10100 5
1$
#1580000
0$
#1585000
b10101 "
b10101 *
b10101 5
1$
#1590000
0$
#1595000
b10110 "
b10110 *
b10110 5
1$
#1600000
0$
#1605000
b10111 "
b10111 *
b10111 5
1$
#1610000
0$
#1615000
b11000 "
b11000 *
b11000 5
1$
#1620000
0$
#1625000
b11001 "
b11001 *
b11001 5
1$
#1630000
0$
#1635000
b11010 "
b11010 *
b11010 5
1$
#1640000
0$
#1645000
b11011 "
b11011 *
b11011 5
1$
#1650000
0$
#1655000
b11100 "
b11100 *
b11100 5
1$
#1660000
0$
#1665000
b11101 "
b11101 *
b11101 5
1$
#1670000
0$
#1675000
b11110 "
b11110 *
b11110 5
1$
#1680000
0$
#1685000
b11111 "
b11111 *
b11111 5
1$
#1690000
0$
#1695000
b100000 "
b100000 *
b100000 5
1$
#1700000
0$
#1705000
b100001 "
b100001 *
b100001 5
1$
#1710000
0$
#1715000
b100010 "
b100010 *
b100010 5
1$
#1720000
0$
#1725000
b100011 "
b100011 *
b100011 5
1$
#1730000
0$
#1735000
b100100 "
b100100 *
b100100 5
1$
#1740000
0$
#1745000
b100101 "
b100101 *
b100101 5
1$
#1750000
0$
#1755000
b100110 "
b100110 *
b100110 5
1$
#1760000
0$
#1765000
b100111 "
b100111 *
b100111 5
1$
#1770000
0$
#1775000
b101000 "
b101000 *
b101000 5
1$
#1780000
0$
#1785000
b101001 "
b101001 *
b101001 5
1$
#1790000
0$
#1795000
b101010 "
b101010 *
b101010 5
1$
#1800000
0$
#1805000
b101011 "
b101011 *
b101011 5
1$
#1810000
0$
#1815000
b101100 "
b101100 *
b101100 5
1$
#1820000
0$
#1825000
b101101 "
b101101 *
b101101 5
1$
#1830000
0$
#1835000
b101110 "
b101110 *
b101110 5
1$
#1840000
0$
#1845000
b101111 "
b101111 *
b101111 5
1$
#1850000
0$
#1855000
b110000 "
b110000 *
b110000 5
1$
#1860000
0$
#1865000
b110001 "
b110001 *
b110001 5
1$
#1870000
0$
#1875000
b110010 "
b110010 *
b110010 5
1$
#1880000
0$
#1885000
b110011 "
b110011 *
b110011 5
1$
#1890000
0$
#1895000
b110100 "
b110100 *
b110100 5
1$
#1900000
0$
#1905000
b110101 "
b110101 *
b110101 5
1$
#1910000
0$
#1915000
b110110 "
b110110 *
b110110 5
1$
#1920000
0$
#1925000
b110111 "
b110111 *
b110111 5
1$
#1930000
0$
#1935000
b111000 "
b111000 *
b111000 5
1$
#1940000
0$
#1945000
b111001 "
b111001 *
b111001 5
1$
#1950000
0$
#1955000
b111010 "
b111010 *
b111010 5
1$
#1960000
0$
#1965000
b111011 "
b111011 *
b111011 5
1$
#1970000
0$
#1975000
1+
b0 "
b0 *
b0 5
1$
#1980000
0$
#1985000
b11 #
b11 ,
b11 4
b1 "
b1 *
b1 5
0+
1$
#1990000
0$
#1995000
b10 "
b10 *
b10 5
1$
#2000000
0$
#2005000
b11 "
b11 *
b11 5
1$
#2010000
0$
#2015000
b100 "
b100 *
b100 5
1$
#2020000
0$
#2025000
b101 "
b101 *
b101 5
1$
#2030000
0$
#2035000
b110 "
b110 *
b110 5
1$
#2040000
0$
#2045000
b111 "
b111 *
b111 5
1$
#2050000
0$
#2055000
b1000 "
b1000 *
b1000 5
1$
#2060000
0$
#2065000
b1001 "
b1001 *
b1001 5
1$
#2070000
0$
#2075000
b1010 "
b1010 *
b1010 5
1$
#2080000
0$
#2085000
b1011 "
b1011 *
b1011 5
1$
#2090000
0$
#2095000
b1100 "
b1100 *
b1100 5
1$
#2100000
0$
#2105000
b1101 "
b1101 *
b1101 5
1$
#2110000
0$
#2115000
b1110 "
b1110 *
b1110 5
1$
#2120000
0$
#2125000
b1111 "
b1111 *
b1111 5
1$
#2130000
0$
#2135000
b10000 "
b10000 *
b10000 5
1$
#2140000
0$
#2145000
b10001 "
b10001 *
b10001 5
1$
#2150000
0$
#2155000
b10010 "
b10010 *
b10010 5
1$
#2160000
0$
#2165000
b10011 "
b10011 *
b10011 5
1$
#2170000
0$
#2175000
b10100 "
b10100 *
b10100 5
1$
#2180000
0$
#2185000
b10101 "
b10101 *
b10101 5
1$
#2190000
0$
#2195000
b10110 "
b10110 *
b10110 5
1$
#2200000
0$
#2205000
b10111 "
b10111 *
b10111 5
1$
#2210000
0$
#2215000
b11000 "
b11000 *
b11000 5
1$
#2220000
0$
#2225000
b11001 "
b11001 *
b11001 5
1$
#2230000
0$
#2235000
b11010 "
b11010 *
b11010 5
1$
#2240000
0$
#2245000
b11011 "
b11011 *
b11011 5
1$
#2250000
0$
#2255000
b11100 "
b11100 *
b11100 5
1$
#2260000
0$
#2265000
b11101 "
b11101 *
b11101 5
1$
#2270000
0$
#2275000
b11110 "
b11110 *
b11110 5
1$
#2280000
0$
#2285000
b11111 "
b11111 *
b11111 5
1$
#2290000
0$
#2295000
b100000 "
b100000 *
b100000 5
1$
#2300000
0$
#2305000
b100001 "
b100001 *
b100001 5
1$
#2310000
0$
#2315000
b100010 "
b100010 *
b100010 5
1$
#2320000
0$
#2325000
b100011 "
b100011 *
b100011 5
1$
#2330000
0$
#2335000
b100100 "
b100100 *
b100100 5
1$
#2340000
0$
#2345000
b100101 "
b100101 *
b100101 5
1$
#2350000
0$
#2355000
b100110 "
b100110 *
b100110 5
1$
#2360000
0$
#2365000
b100111 "
b100111 *
b100111 5
1$
#2370000
0$
#2375000
b101000 "
b101000 *
b101000 5
1$
#2380000
0$
#2385000
b101001 "
b101001 *
b101001 5
1$
#2390000
0$
#2395000
b101010 "
b101010 *
b101010 5
1$
#2400000
0$
#2405000
b101011 "
b101011 *
b101011 5
1$
#2410000
0$
#2415000
b101100 "
b101100 *
b101100 5
1$
#2420000
0$
#2425000
b101101 "
b101101 *
b101101 5
1$
#2430000
0$
#2435000
b101110 "
b101110 *
b101110 5
1$
#2440000
0$
#2445000
b101111 "
b101111 *
b101111 5
1$
#2450000
0$
#2455000
b110000 "
b110000 *
b110000 5
1$
#2460000
0$
#2465000
b110001 "
b110001 *
b110001 5
1$
#2470000
0$
#2475000
b110010 "
b110010 *
b110010 5
1$
#2480000
0$
#2485000
b110011 "
b110011 *
b110011 5
1$
#2490000
0$
#2495000
b110100 "
b110100 *
b110100 5
1$
#2500000
0$
#2505000
b110101 "
b110101 *
b110101 5
1$
#2510000
0$
#2515000
b110110 "
b110110 *
b110110 5
1$
#2520000
0$
#2525000
b110111 "
b110111 *
b110111 5
1$
#2530000
0$
#2535000
b111000 "
b111000 *
b111000 5
1$
#2540000
0$
#2545000
b111001 "
b111001 *
b111001 5
1$
#2550000
0$
#2555000
b111010 "
b111010 *
b111010 5
1$
#2560000
0$
#2565000
b111011 "
b111011 *
b111011 5
1$
#2570000
0$
#2575000
1+
b0 "
b0 *
b0 5
1$
#2580000
0$
#2585000
b100 #
b100 ,
b100 4
b1 "
b1 *
b1 5
0+
1$
#2590000
0$
#2595000
b10 "
b10 *
b10 5
1$
#2600000
0$
#2605000
b11 "
b11 *
b11 5
1$
#2610000
0$
#2615000
b100 "
b100 *
b100 5
1$
#2620000
0$
#2625000
b101 "
b101 *
b101 5
1$
#2630000
0$
#2635000
b110 "
b110 *
b110 5
1$
#2640000
0$
#2645000
b111 "
b111 *
b111 5
1$
#2650000
0$
#2655000
b1000 "
b1000 *
b1000 5
1$
#2660000
0$
#2665000
b1001 "
b1001 *
b1001 5
1$
#2670000
0$
#2675000
b1010 "
b1010 *
b1010 5
1$
#2680000
0$
#2685000
b1011 "
b1011 *
b1011 5
1$
#2690000
0$
#2695000
b1100 "
b1100 *
b1100 5
1$
#2700000
0$
#2705000
b1101 "
b1101 *
b1101 5
1$
#2710000
0$
#2715000
b1110 "
b1110 *
b1110 5
1$
#2720000
0$
#2725000
b1111 "
b1111 *
b1111 5
1$
#2730000
0$
#2735000
b10000 "
b10000 *
b10000 5
1$
#2740000
0$
#2745000
b10001 "
b10001 *
b10001 5
1$
#2750000
0$
#2755000
b10010 "
b10010 *
b10010 5
1$
#2760000
0$
#2765000
b10011 "
b10011 *
b10011 5
1$
#2770000
0$
#2775000
b10100 "
b10100 *
b10100 5
1$
#2780000
0$
#2785000
b10101 "
b10101 *
b10101 5
1$
#2790000
0$
#2795000
b10110 "
b10110 *
b10110 5
1$
#2800000
0$
#2805000
b10111 "
b10111 *
b10111 5
1$
#2810000
0$
#2815000
b11000 "
b11000 *
b11000 5
1$
#2820000
0$
#2825000
b11001 "
b11001 *
b11001 5
1$
#2830000
0$
#2835000
b11010 "
b11010 *
b11010 5
1$
#2840000
0$
#2845000
b11011 "
b11011 *
b11011 5
1$
#2850000
0$
#2855000
b11100 "
b11100 *
b11100 5
1$
#2860000
0$
#2865000
b11101 "
b11101 *
b11101 5
1$
#2870000
0$
#2875000
b11110 "
b11110 *
b11110 5
1$
#2880000
0$
#2885000
b11111 "
b11111 *
b11111 5
1$
#2890000
0$
#2895000
b100000 "
b100000 *
b100000 5
1$
#2900000
0$
#2905000
b100001 "
b100001 *
b100001 5
1$
#2910000
0$
#2915000
b100010 "
b100010 *
b100010 5
1$
#2920000
0$
#2925000
b100011 "
b100011 *
b100011 5
1$
#2930000
0$
#2935000
b100100 "
b100100 *
b100100 5
1$
#2940000
0$
#2945000
b100101 "
b100101 *
b100101 5
1$
#2950000
0$
#2955000
b100110 "
b100110 *
b100110 5
1$
#2960000
0$
#2965000
b100111 "
b100111 *
b100111 5
1$
#2970000
0$
#2975000
b101000 "
b101000 *
b101000 5
1$
#2980000
0$
#2985000
b101001 "
b101001 *
b101001 5
1$
#2990000
0$
#2995000
b101010 "
b101010 *
b101010 5
1$
#3000000
0$
#3005000
b101011 "
b101011 *
b101011 5
1$
#3010000
0$
#3015000
b101100 "
b101100 *
b101100 5
1$
#3020000
0$
#3025000
b101101 "
b101101 *
b101101 5
1$
#3030000
0$
#3035000
b101110 "
b101110 *
b101110 5
1$
#3040000
0$
#3045000
b101111 "
b101111 *
b101111 5
1$
#3050000
0$
#3055000
b110000 "
b110000 *
b110000 5
1$
#3060000
0$
#3065000
b110001 "
b110001 *
b110001 5
1$
#3070000
0$
#3075000
b110010 "
b110010 *
b110010 5
1$
#3080000
0$
#3085000
b110011 "
b110011 *
b110011 5
1$
#3090000
0$
#3095000
b110100 "
b110100 *
b110100 5
1$
#3100000
0$
#3105000
b110101 "
b110101 *
b110101 5
1$
#3110000
0$
#3115000
b110110 "
b110110 *
b110110 5
1$
#3120000
0$
#3125000
b110111 "
b110111 *
b110111 5
1$
#3130000
0$
#3135000
b111000 "
b111000 *
b111000 5
1$
#3140000
0$
#3145000
b111001 "
b111001 *
b111001 5
1$
#3150000
0$
#3155000
b111010 "
b111010 *
b111010 5
1$
#3160000
0$
#3165000
b111011 "
b111011 *
b111011 5
1$
#3170000
0$
#3175000
1+
b0 "
b0 *
b0 5
1$
#3180000
0$
#3185000
b101 #
b101 ,
b101 4
b1 "
b1 *
b1 5
0+
1$
#3190000
0$
#3195000
b10 "
b10 *
b10 5
1$
#3200000
0$
#3205000
b11 "
b11 *
b11 5
1$
#3210000
0$
#3215000
b100 "
b100 *
b100 5
1$
#3220000
0$
#3225000
b101 "
b101 *
b101 5
1$
#3230000
0$
#3235000
b110 "
b110 *
b110 5
1$
#3240000
0$
#3245000
b111 "
b111 *
b111 5
1$
#3250000
0$
#3255000
b1000 "
b1000 *
b1000 5
1$
#3260000
0$
#3265000
b1001 "
b1001 *
b1001 5
1$
#3270000
0$
#3275000
b1010 "
b1010 *
b1010 5
1$
#3280000
0$
#3285000
b1011 "
b1011 *
b1011 5
1$
#3290000
0$
#3295000
b1100 "
b1100 *
b1100 5
1$
#3300000
0$
#3305000
b1101 "
b1101 *
b1101 5
1$
#3310000
0$
#3315000
b1110 "
b1110 *
b1110 5
1$
#3320000
0$
#3325000
b1111 "
b1111 *
b1111 5
1$
#3330000
0$
#3335000
b10000 "
b10000 *
b10000 5
1$
#3340000
0$
#3345000
b10001 "
b10001 *
b10001 5
1$
#3350000
0$
#3355000
b10010 "
b10010 *
b10010 5
1$
#3360000
0$
#3365000
b10011 "
b10011 *
b10011 5
1$
#3370000
0$
#3375000
b10100 "
b10100 *
b10100 5
1$
#3380000
0$
#3385000
b10101 "
b10101 *
b10101 5
1$
#3390000
0$
#3395000
b10110 "
b10110 *
b10110 5
1$
#3400000
0$
#3405000
b10111 "
b10111 *
b10111 5
1$
#3410000
0$
#3415000
b11000 "
b11000 *
b11000 5
1$
#3420000
0$
#3425000
b11001 "
b11001 *
b11001 5
1$
#3430000
0$
#3435000
b11010 "
b11010 *
b11010 5
1$
#3440000
0$
#3445000
b11011 "
b11011 *
b11011 5
1$
#3450000
0$
#3455000
b11100 "
b11100 *
b11100 5
1$
#3460000
0$
#3465000
b11101 "
b11101 *
b11101 5
1$
#3470000
0$
#3475000
b11110 "
b11110 *
b11110 5
1$
#3480000
0$
#3485000
b11111 "
b11111 *
b11111 5
1$
#3490000
0$
#3495000
b100000 "
b100000 *
b100000 5
1$
#3500000
0$
#3505000
b100001 "
b100001 *
b100001 5
1$
#3510000
0$
#3515000
b100010 "
b100010 *
b100010 5
1$
#3520000
0$
#3525000
b100011 "
b100011 *
b100011 5
1$
#3530000
0$
#3535000
b100100 "
b100100 *
b100100 5
1$
#3540000
0$
#3545000
b100101 "
b100101 *
b100101 5
1$
#3550000
0$
#3555000
b100110 "
b100110 *
b100110 5
1$
#3560000
0$
#3565000
b100111 "
b100111 *
b100111 5
1$
#3570000
0$
